pyccsi/__init__.py
pyccsi/downloader.py
pyccsi/facade.py
pyccsi/parser.py
pyccsi/schema.py
pyccsi-1.0.1.dist-info/METADATA
pyccsi-1.0.1.dist-info/WHEEL
pyccsi-1.0.1.dist-info/top_level.txt
pyccsi-1.0.1.dist-info/RECORD
