Metadata-Version: 2.1
Name: pyccsi
Version: 1.0.1
Summary: Python package for request and download data from CCSI 
Home-page: https://github.com/gisat/pyccsi
Author: Michal Opletal
Author-email: michal.opletal@gisat.cz
License: MIT
Platform: UNKNOWN
Classifier: License :: OSI Approved :: MIT License
Classifier: Programming Language :: Python :: 3.10
Requires-Dist: pydantic (>=1.10.2)
Requires-Dist: setuptools (>=58.5.3)
Requires-Dist: requests (>=2.28.1)
Requires-Dist: termcolor (>=2.1.0)
